LICENSE.txt
README.md
pyproject.toml
netboxlabs/diode/scripts/__init__.py
netboxlabs/diode/scripts/dryrun_replay.py
netboxlabs/diode/sdk/__init__.py
netboxlabs/diode/sdk/chunking.py
netboxlabs/diode/sdk/client.py
netboxlabs/diode/sdk/client.pyi
netboxlabs/diode/sdk/exceptions.py
netboxlabs/diode/sdk/ingester.py
netboxlabs/diode/sdk/version.py
netboxlabs/diode/sdk/diode/__init__.py
netboxlabs/diode/sdk/diode/v1/__init__.py
netboxlabs/diode/sdk/diode/v1/ingester_pb2.py
netboxlabs/diode/sdk/diode/v1/ingester_pb2.pyi
netboxlabs/diode/sdk/diode/v1/ingester_pb2_grpc.py
netboxlabs/diode/sdk/validate/__init__.py
netboxlabs/diode/sdk/validate/validate_pb2.py
netboxlabs/diode/sdk/validate/validate_pb2.pyi
netboxlabs/diode/sdk/validate/validate_pb2_grpc.py
netboxlabs_diode_sdk.egg-info/PKG-INFO
netboxlabs_diode_sdk.egg-info/SOURCES.txt
netboxlabs_diode_sdk.egg-info/dependency_links.txt
netboxlabs_diode_sdk.egg-info/entry_points.txt
netboxlabs_diode_sdk.egg-info/requires.txt
netboxlabs_diode_sdk.egg-info/top_level.txt
tests/test_chunking.py
tests/test_client.py
tests/test_ingester.py
tests/test_version.py