Metadata-Version: 2.4
Name: netboxlabs-diode-sdk
Version: 1.9.0
Summary: NetBox Labs, Diode SDK
Author-email: NetBox Labs <support@netboxlabs.com>
Maintainer-email: NetBox Labs <support@netboxlabs.com>
License:                                  Apache License
Project-URL: Homepage, https://netboxlabs.com/
Classifier: Development Status :: 4 - Beta
Classifier: Intended Audience :: Developers
Classifier: Topic :: Software Development :: Build Tools
Classifier: License :: OSI Approved :: Apache Software License
Classifier: Programming Language :: Python :: 3
Classifier: Programming Language :: Python :: 3 :: Only
Classifier: Programming Language :: Python :: 3.10
Classifier: Programming Language :: Python :: 3.11
Requires-Python: >=3.10
License-File: LICENSE.txt
Requires-Dist: certifi>=2024.7.4
Requires-Dist: grpcio>=1.68.1
Requires-Dist: grpcio-status>=1.68.1
Requires-Dist: requests>=2.31.0
Requires-Dist: sentry-sdk>=2.2.1
Requires-Dist: opentelemetry-proto>=1.26.0
Provides-Extra: dev
Requires-Dist: black; extra == "dev"
Requires-Dist: check-manifest; extra == "dev"
Requires-Dist: ruff; extra == "dev"
Provides-Extra: test
Requires-Dist: coverage; extra == "test"
Requires-Dist: pytest; extra == "test"
Requires-Dist: pytest-cov==6.0.0; extra == "test"
Dynamic: license-file
